RunDB/__init__.py
RunDB/database.py
RunDB/defaults.py
RunDB/record.py
RunDB/recordset.py
RunDB/relational.py
RunDB/table.py
RunDB/test.py
RunDB/tools/__init__.py
RunDB/tools/path.py
RunDB/tools/serialization.py
rundb-0.6.dist-info/LICENSE
rundb-0.6.dist-info/METADATA
rundb-0.6.dist-info/WHEEL
rundb-0.6.dist-info/top_level.txt
rundb-0.6.dist-info/RECORD
