Metadata-Version: 2.1
Name: rundb
Version: 0.6
Summary: A pseudo NoSQL database
Home-page: https://github.com/divad1196/RunDB
Author: Gallay David
Author-email: davidtennis96@hotmail.com
License: UNKNOWN
Platform: UNKNOWN
Classifier: Programming Language :: Python :: 3
Classifier: License :: OSI Approved :: MIT License
Classifier: Operating System :: OS Independent
